{
  "id": "e5d98577-fe46-4830-a5f2-b26a132db359",
  "prevId": "00000000-0000-0000-0000-000000000000",
  "version": "7",
  "dialect": "postgresql",
  "tables": {
    "public.categories": {
      "name": "categories",
      "schema": "",
      "columns": {
        "id": {
          "name": "id",
          "type": "serial",
          "primaryKey": true,
          "notNull": true
        },
        "title": {
          "name": "title",
          "type": "varchar(255)",
          "primaryKey": false,
          "notNull": true
        },
        "path": {
          "name": "path",
          "type": "varchar(255)",
          "primaryKey": false,
          "notNull": true
        },
        "url": {
          "name": "url",
          "type": "varchar(255)",
          "primaryKey": false,
          "notNull": false
        }
      },
      "indexes": {},
      "foreignKeys": {},
      "compositePrimaryKeys": {},
      "uniqueConstraints": {},
      "policies": {},
      "checkConstraints": {},
      "isRLSEnabled": false
    },
    "public.goods": {
      "name": "goods",
      "schema": "",
      "columns": {
        "id": {
          "name": "id",
          "type": "serial",
          "primaryKey": true,
          "notNull": true
        },
        "title": {
          "name": "title",
          "type": "varchar(256)",
          "primaryKey": false,
          "notNull": true
        },
        "quantity": {
          "name": "quantity",
          "type": "integer",
          "primaryKey": false,
          "notNull": true
        },
        "createdAt": {
          "name": "createdAt",
          "type": "timestamp",
          "primaryKey": false,
          "notNull": true,
          "default": "now()"
        },
        "updatedAt": {
          "name": "updatedAt",
          "type": "timestamp",
          "primaryKey": false,
          "notNull": true,
          "default": "CURRENT_TIMESTAMP"
        }
      },
      "indexes": {},
      "foreignKeys": {},
      "compositePrimaryKeys": {},
      "uniqueConstraints": {},
      "policies": {},
      "checkConstraints": {},
      "isRLSEnabled": false
    },
    "public.users": {
      "name": "users",
      "schema": "",
      "columns": {
        "id": {
          "name": "id",
          "type": "serial",
          "primaryKey": true,
          "notNull": true
        },
        "username": {
          "name": "username",
          "type": "varchar(255)",
          "primaryKey": false,
          "notNull": false
        },
        "created_at": {
          "name": "created_at",
          "type": "date",
          "primaryKey": false,
          "notNull": true,
          "default": "now()"
        },
        "updated_at": {
          "name": "updated_at",
          "type": "date",
          "primaryKey": false,
          "notNull": false,
          "default": "(CURRENT_DATE)"
        },
        "personal_info_id": {
          "name": "personal_info_id",
          "type": "integer",
          "primaryKey": false,
          "notNull": false
        }
      },
      "indexes": {},
      "foreignKeys": {},
      "compositePrimaryKeys": {},
      "uniqueConstraints": {},
      "policies": {},
      "checkConstraints": {},
      "isRLSEnabled": false
    },
    "public.subcategories": {
      "name": "subcategories",
      "schema": "",
      "columns": {
        "id": {
          "name": "id",
          "type": "serial",
          "primaryKey": true,
          "notNull": true
        },
        "title": {
          "name": "title",
          "type": "varchar(255)",
          "primaryKey": false,
          "notNull": true
        },
        "path": {
          "name": "path",
          "type": "varchar(255)",
          "primaryKey": false,
          "notNull": true
        },
        "url": {
          "name": "url",
          "type": "varchar(255)",
          "primaryKey": false,
          "notNull": false
        },
        "categoryId": {
          "name": "categoryId",
          "type": "integer",
          "primaryKey": false,
          "notNull": false
        }
      },
      "indexes": {},
      "foreignKeys": {},
      "compositePrimaryKeys": {},
      "uniqueConstraints": {},
      "policies": {},
      "checkConstraints": {},
      "isRLSEnabled": false
    },
    "public.personal-info": {
      "name": "personal-info",
      "schema": "",
      "columns": {
        "id": {
          "name": "id",
          "type": "serial",
          "primaryKey": true,
          "notNull": true
        },
        "user_id": {
          "name": "user_id",
          "type": "integer",
          "primaryKey": false,
          "notNull": false
        },
        "firstName": {
          "name": "firstName",
          "type": "varchar(255)",
          "primaryKey": false,
          "notNull": false
        },
        "lastName": {
          "name": "lastName",
          "type": "varchar(255)",
          "primaryKey": false,
          "notNull": false
        },
        "middleName": {
          "name": "middleName",
          "type": "varchar(255)",
          "primaryKey": false,
          "notNull": false
        },
        "birthDate": {
          "name": "birthDate",
          "type": "date",
          "primaryKey": false,
          "notNull": false
        },
        "avatarFileName": {
          "name": "avatarFileName",
          "type": "text",
          "primaryKey": false,
          "notNull": false
        }
      },
      "indexes": {},
      "foreignKeys": {
        "personal-info_user_id_users_id_fk": {
          "name": "personal-info_user_id_users_id_fk",
          "tableFrom": "personal-info",
          "tableTo": "users",
          "columnsFrom": [
            "user_id"
          ],
          "columnsTo": [
            "id"
          ],
          "onDelete": "no action",
          "onUpdate": "no action"
        }
      },
      "compositePrimaryKeys": {},
      "uniqueConstraints": {},
      "policies": {},
      "checkConstraints": {},
      "isRLSEnabled": false
    }
  },
  "enums": {},
  "schemas": {},
  "sequences": {},
  "roles": {},
  "policies": {},
  "views": {},
  "_meta": {
    "columns": {},
    "schemas": {},
    "tables": {}
  }
}